not_sklearn/classification/LogisticRegression.py
not_sklearn/classification/__init__.py
not_sklearn/regression/LinearRegression.py
not_sklearn/regression/__init__.py
not_sklearn-0.0.1.dist-info/METADATA
not_sklearn-0.0.1.dist-info/WHEEL
not_sklearn-0.0.1.dist-info/licenses/LICENSE
not_sklearn-0.0.1.dist-info/RECORD
